Metadata-Version: 2.0
Name: cython-construct
Version: 2.5.8
Summary: A powerful declarative parser/builder for binary data
Home-page: http://construct.readthedocs.org
Author: Tomer Filiba, Corbin Simpson
Author-email: tomerfiliba@gmail.com, MostAwesomeDude@gmail.com
License: MIT
Keywords: construct,declarative,data structure,binary,parser,builder,pack,unpack
Platform: POSIX
Platform: Windows
Classifier: Development Status :: 5 - Production/Stable
Classifier: License :: OSI Approved :: MIT License
Classifier: Programming Language :: Python :: 2
Classifier: Programming Language :: Python :: 3
Classifier: Programming Language :: Python :: 2.7
Classifier: Programming Language :: Python :: 3.3
Classifier: Programming Language :: Python :: 3.4
Classifier: Programming Language :: Python :: 3.5
Provides: construct
